Metadata-Version: 2.1
Name: pygads
Version: 0.0.7
Summary: A Google Ads connector
Home-page: https://github.com/dacker-team/pygads
Author: Dacker
Author-email: hello@dacker.co
License: UNKNOWN
Platform: UNKNOWN
Classifier: Programming Language :: Python :: 3
Classifier: License :: OSI Approved :: MIT License
Classifier: Operating System :: OS Independent
Requires-Python: >=3
